matrix_stickers_manager/__init__.py
matrix_stickers_manager/manager.py
matrix_stickers_manager-0.4.dist-info/WHEEL
matrix_stickers_manager-0.4.dist-info/METADATA
matrix_stickers_manager-0.4.dist-info/RECORD
