Metadata-Version: 2.1
Name: matrix_stickers_manager
Version: 0.4
Summary: matrix_stickers_manager
Author-email: foresle <foresle@tutanota.com>
Requires-Dist: pytest~=7.2.1
Requires-Dist: environs~=9.5.0
Requires-Dist: requests~=2.28.2
Requires-Dist: filetype~=1.2.0
Requires-Dist: dataclass_wizard~=0.22.2
Project-URL: Home, https://github.com/foresle/matrix_stickers_manager
